efj_parser/__init__.py
efj_parser/py.typed
efj_parser-0.9.4.dist-info/LICENSE
efj_parser-0.9.4.dist-info/METADATA
efj_parser-0.9.4.dist-info/WHEEL
efj_parser-0.9.4.dist-info/top_level.txt
efj_parser-0.9.4.dist-info/RECORD
