Metadata-Version: 2.2
Name: efj-parser
Version: 0.9.4
Summary: Parse an electronic Flight Journal file
Home-page: https://github.com/JonHurst/efj_parser
Author: Jon Hurst
Author-email: jon.a@hursts.org.uk
Project-URL: docs, https://hursts.org.uk/efjdocs/
Classifier: Development Status :: 4 - Beta
Classifier: Programming Language :: Python :: 3
Classifier: License :: OSI Approved :: GNU General Public License v3 or later (GPLv3+)
Classifier: Operating System :: OS Independent
Requires-Python: >=3.11
License-File: LICENSE
Dynamic: author
Dynamic: author-email
Dynamic: classifier
Dynamic: description
Dynamic: description-content-type
Dynamic: home-page
Dynamic: project-url
Dynamic: requires-python
Dynamic: summary
